codicodec/__init__.py
codicodec/audio.py
codicodec/hparams.py
codicodec/hparams_inference.py
codicodec/inference.py
codicodec/models.py
codicodec/transformer.py
codicodec/transformer_layers.py
codicodec/utils.py
codicodec-0.1.1.dist-info/LICENSE
codicodec-0.1.1.dist-info/METADATA
codicodec-0.1.1.dist-info/WHEEL
codicodec-0.1.1.dist-info/top_level.txt
codicodec-0.1.1.dist-info/RECORD
