Metadata-Version: 2.1
Name: codicodec
Version: 0.1.1
Summary: Encode and decode audio samples to/from continuous and discrete compressed representations!
Home-page: https://github.com/SonyCSLParis/codicodec
Author: Sony Computer Science Laboratories Paris
Author-email: music@csl.sony.fr
License: CC BY-NC 4.0
Keywords: audio speech music codec compression generative-model autoencoder diffusion continuous discrete latent
License-File: LICENSE
Requires-Dist: numpy
Requires-Dist: einops
Requires-Dist: soundfile
Requires-Dist: huggingface-hub
Requires-Dist: librosa
Requires-Dist: torch
